{
  "metadata": {
    "Artist": "Kairiki bear",
    "AssetId": "rbxassetid://5837530414",
    "CoverImageAssetId": "",
    "Description": "",
    "Difficulty": 31,
    "Filename": "Venom [Cut ver.] (LN)",
    "HitSFXGroup": 0,
    "MD5Hash": "35406c263c3bea0ec25c1e6a5d643648",
    "NotePrebufferTime": 1000,
    "TimeOffset": -70,
    "Volume": 0.5
  },
  "objects": [
    {
      "Time": 1178,
      "Track": 2
    },
    {
      "Time": 1178,
      "Track": 1
    },
    {
      "Time": 1178,
      "Track": 4
    },
    {
      "Time": 1572,
      "Track": 2
    },
    {
      "Time": 1572,
      "Track": 1
    },
    {
      "Time": 1572,
      "Track": 4
    },
    {
      "Duration": 297,
      "Time": 1572,
      "Track": 3
    },
    {
      "Duration": 296,
      "Time": 1770,
      "Track": 2
    },
    {
      "Time": 1968,
      "Track": 4
    },
    {
      "Time": 1968,
      "Track": 1
    },
    {
      "Duration": 296,
      "Time": 1968,
      "Track": 3
    },
    {
      "Duration": 395,
      "Time": 2165,
      "Track": 2
    },
    {
      "Time": 2362,
      "Track": 1
    },
    {
      "Duration": 296,
      "Time": 2362,
      "Track": 3
    },
    {
      "Time": 2560,
      "Track": 4
    },
    {
      "Duration": 99,
      "Time": 2658,
      "Track": 1
    },
    {
      "Time": 2757,
      "Track": 3
    },
    {
      "Time": 2757,
      "Track": 2
    },
    {
      "Time": 2757,
      "Track": 4
    },
    {
      "Duration": 494,
      "Time": 2954,
      "Track": 2
    },
    {
      "Time": 3152,
      "Track": 3
    },
    {
      "Time": 3152,
      "Track": 4
    },
    {
      "Duration": 395,
      "Time": 3349,
      "Track": 1
    },
    {
      "Duration": 198,
      "Time": 3546,
      "Track": 2
    },
    {
      "Time": 3546,
      "Track": 4
    },
    {
      "Time": 3546,
      "Track": 3
    },
    {
      "Duration": 395,
      "Time": 3744,
      "Track": 3
    },
    {
      "Duration": 198,
      "Time": 3941,
      "Track": 4
    },
    {
      "Time": 3941,
      "Track": 2
    },
    {
      "Time": 4139,
      "Track": 1
    },
    {
      "Time": 4237,
      "Track": 2
    },
    {
      "Time": 4336,
      "Track": 1
    },
    {
      "Duration": 395,
      "Time": 4336,
      "Track": 4
    },
    {
      "Duration": 296,
      "Time": 4336,
      "Track": 3
    },
    {
      "Time": 4533,
      "Track": 2
    },
    {
      "Time": 4731,
      "Track": 1
    },
    {
      "Duration": 296,
      "Time": 4731,
      "Track": 3
    },
    {
      "Duration": 296,
      "Time": 4928,
      "Track": 1
    },
    {
      "Duration": 296,
      "Time": 5125,
      "Track": 3
    },
    {
      "Time": 5125,
      "Track": 2
    },
    {
      "Time": 5125,
      "Track": 4
    },
    {
      "Duration": 395,
      "Time": 5323,
      "Track": 1
    },
    {
      "Duration": 296,
      "Time": 5520,
      "Track": 3
    },
    {
      "Time": 5520,
      "Track": 4
    },
    {
      "Time": 5718,
      "Track": 2
    },
    {
      "Duration": 99,
      "Time": 5816,
      "Track": 4
    },
    {
      "Time": 5915,
      "Track": 3
    },
    {
      "Time": 5915,
      "Track": 2
    },
    {
      "Time": 5915,
      "Track": 1
    },
    {
      "Duration": 494,
      "Time": 6112,
      "Track": 3
    },
    {
      "Time": 6310,
      "Track": 4
    },
    {
      "Time": 6310,
      "Track": 1
    },
    {
      "Duration": 395,
      "Time": 6507,
      "Track": 2
    },
    {
      "Duration": 198,
      "Time": 6704,
      "Track": 3
    },
    {
      "Time": 6704,
      "Track": 1
    },
    {
      "Time": 6704,
      "Track": 4
    },
    {
      "Duration": 394,
      "Time": 6902,
      "Track": 4
    },
    {
      "Duration": 197,
      "Time": 7099,
      "Track": 1
    },
    {
      "Time": 7099,
      "Track": 2
    },
    {
      "Time": 7296,
      "Track": 3
    },
    {
      "Time": 7395,
      "Track": 2
    },
    {
      "Time": 7494,
      "Track": 3
    },
    {
      "Duration": 395,
      "Time": 7494,
      "Track": 1
    },
    {
      "Duration": 296,
      "Time": 7494,
      "Track": 4
    },
    {
      "Time": 7691,
      "Track": 2
    },
    {
      "Time": 7889,
      "Track": 2
    },
    {
      "Time": 7889,
      "Track": 3
    },
    {
      "Duration": 296,
      "Time": 7889,
      "Track": 4
    },
    {
      "Duration": 296,
      "Time": 8086,
      "Track": 1
    },
    {
      "Duration": 296,
      "Time": 8283,
      "Track": 4
    },
    {
      "Time": 8283,
      "Track": 2
    },
    {
      "Time": 8283,
      "Track": 3
    },
    {
      "Duration": 394,
      "Time": 8481,
      "Track": 1
    },
    {
      "Duration": 296,
      "Time": 8678,
      "Track": 3
    },
    {
      "Time": 8678,
      "Track": 4
    },
    {
      "Time": 8875,
      "Track": 2
    },
    {
      "Duration": 99,
      "Time": 8974,
      "Track": 4
    },
    {
      "Time": 9073,
      "Track": 3
    },
    {
      "Time": 9073,
      "Track": 1
    },
    {
      "Time": 9073,
      "Track": 2
    },
    {
      "Duration": 494,
      "Time": 9270,
      "Track": 1
    },
    {
      "Time": 9468,
      "Track": 4
    },
    {
      "Time": 9468,
      "Track": 3
    },
    {
      "Duration": 395,
      "Time": 9665,
      "Track": 3
    },
    {
      "Duration": 198,
      "Time": 9862,
      "Track": 1
    },
    {
      "Time": 9862,
      "Track": 2
    },
    {
      "Time": 9862,
      "Track": 4
    },
    {
      "Duration": 394,
      "Time": 10060,
      "Track": 2
    },
    {
      "Duration": 197,
      "Time": 10257,
      "Track": 4
    },
    {
      "Time": 10257,
      "Track": 1
    },
    {
      "Time": 10454,
      "Track": 3
    },
    {
      "Time": 10553,
      "Track": 1
    },
    {
      "Time": 10652,
      "Track": 4
    },
    {
      "Duration": 296,
      "Time": 10652,
      "Track": 2
    },
    {
      "Duration": 394,
      "Time": 10652,
      "Track": 3
    },
    {
      "Time": 10849,
      "Track": 1
    },
    {
      "Time": 11046,
      "Track": 2
    },
    {
      "Duration": 297,
      "Time": 11046,
      "Track": 4
    },
    {
      "Duration": 296,
      "Time": 11244,
      "Track": 1
    },
    {
      "Duration": 296,
      "Time": 11441,
      "Track": 4
    },
    {
      "Time": 11441,
      "Track": 3
    },
    {
      "Time": 11441,
      "Track": 2
    },
    {
      "Duration": 394,
      "Time": 11639,
      "Track": 1
    },
    {
      "Duration": 296,
      "Time": 11836,
      "Track": 2
    },
    {
      "Time": 11836,
      "Track": 4
    },
    {
      "Time": 12033,
      "Track": 3
    },
    {
      "Duration": 99,
      "Time": 12132,
      "Track": 4
    },
    {
      "Time": 12231,
      "Track": 3
    },
    {
      "Time": 12231,
      "Track": 2
    },
    {
      "Time": 12231,
      "Track": 1
    },
    {
      "Duration": 493,
      "Time": 12428,
      "Track": 1
    },
    {
      "Time": 12625,
      "Track": 4
    },
    {
      "Time": 12625,
      "Track": 2
    },
    {
      "Duration": 395,
      "Time": 12823,
      "Track": 3
    },
    {
      "Duration": 198,
      "Time": 13020,
      "Track": 2
    },
    {
      "Time": 13020,
      "Track": 4
    },
    {
      "Time": 13020,
      "Track": 1
    },
    {
      "Duration": 394,
      "Time": 13218,
      "Track": 1
    },
    {
      "Duration": 197,
      "Time": 13415,
      "Track": 4
    },
    {
      "Time": 13415,
      "Track": 2
    },
    {
      "Time": 13612,
      "Track": 3
    },
    {
      "Time": 13711,
      "Track": 2
    },
    {
      "Time": 13810,
      "Track": 4
    },
    {
      "Duration": 296,
      "Time": 13810,
      "Track": 1
    },
    {
      "Duration": 394,
      "Time": 13810,
      "Track": 3
    },
    {
      "Time": 14007,
      "Track": 2
    },
    {
      "Time": 14204,
      "Track": 1
    },
    {
      "Time": 14204,
      "Track": 2
    },
    {
      "Time": 14204,
      "Track": 4
    },
    {
      "Time": 14303,
      "Track": 3
    },
    {
      "Duration": 197,
      "Time": 14402,
      "Track": 4
    },
    {
      "Time": 14599,
      "Track": 2
    },
    {
      "Time": 14599,
      "Track": 3
    },
    {
      "Duration": 197,
      "Time": 14599,
      "Track": 1
    },
    {
      "Duration": 198,
      "Time": 14796,
      "Track": 3
    },
    {
      "Duration": 296,
      "Time": 14994,
      "Track": 2
    },
    {
      "Time": 14994,
      "Track": 4
    },
    {
      "Time": 15191,
      "Track": 1
    },
    {
      "Duration": 99,
      "Time": 15290,
      "Track": 3
    },
    {
      "Time": 15389,
      "Track": 4
    },
    {
      "Time": 15389,
      "Track": 2
    },
    {
      "Time": 15389,
      "Track": 1
    },
    {
      "Time": 15586,
      "Track": 3
    },
    {
      "Time": 15685,
      "Track": 2
    },
    {
      "Duration": 198,
      "Time": 15783,
      "Track": 3
    },
    {
      "Time": 15783,
      "Track": 4
    },
    {
      "Duration": 197,
      "Time": 15981,
      "Track": 1
    },
    {
      "Time": 16178,
      "Track": 3
    },
    {
      "Duration": 197,
      "Time": 16178,
      "Track": 4
    },
    {
      "Time": 16178,
      "Track": 2
    },
    {
      "Duration": 198,
      "Time": 16375,
      "Track": 3
    },
    {
      "Duration": 197,
      "Time": 16573,
      "Track": 2
    },
    {
      "Time": 16573,
      "Track": 1
    },
    {
      "Duration": 198,
      "Time": 16770,
      "Track": 4
    },
    {
      "Time": 16968,
      "Track": 3
    },
    {
      "Time": 16968,
      "Track": 2
    },
    {
      "Time": 16968,
      "Track": 1
    },
    {
      "Time": 17066,
      "Track": 4
    },
    {
      "Duration": 197,
      "Time": 17165,
      "Track": 3
    },
    {
      "Time": 17362,
      "Track": 4
    },
    {
      "Duration": 198,
      "Time": 17362,
      "Track": 1
    },
    {
      "Duration": 197,
      "Time": 17560,
      "Track": 2
    },
    {
      "Time": 17757,
      "Track": 3
    },
    {
      "Time": 17757,
      "Track": 1
    },
    {
      "Duration": 197,
      "Time": 17757,
      "Track": 4
    },
    {
      "Duration": 198,
      "Time": 17954,
      "Track": 3
    },
    {
      "Time": 18152,
      "Track": 4
    },
    {
      "Duration": 296,
      "Time": 18152,
      "Track": 1
    },
    {
      "Time": 18349,
      "Track": 3
    },
    {
      "Duration": 98,
      "Time": 18448,
      "Track": 2
    },
    {
      "Time": 18546,
      "Track": 3
    },
    {
      "Time": 18546,
      "Track": 4
    },
    {
      "Time": 18546,
      "Track": 1
    },
    {
      "Time": 18744,
      "Track": 2
    },
    {
      "Time": 18843,
      "Track": 3
    },
    {
      "Time": 18941,
      "Track": 1
    },
    {
      "Duration": 198,
      "Time": 18941,
      "Track": 4
    },
    {
      "Duration": 197,
      "Time": 19139,
      "Track": 2
    },
    {
      "Time": 19336,
      "Track": 3
    },
    {
      "Time": 19336,
      "Track": 4
    },
    {
      "Duration": 197,
      "Time": 19336,
      "Track": 1
    },
    {
      "Duration": 198,
      "Time": 19533,
      "Track": 3
    },
    {
      "Duration": 197,
      "Time": 19731,
      "Track": 4
    },
    {
      "Time": 19731,
      "Track": 2
    },
    {
      "Time": 19928,
      "Track": 1
    },
    {
      "Time": 20027,
      "Track": 2
    },
    {
      "Duration": 296,
      "Time": 20125,
      "Track": 1
    },
    {
      "Time": 20125,
      "Track": 3
    },
    {
      "Time": 20125,
      "Track": 4
    },
    {
      "Time": 20323,
      "Track": 2
    },
    {
      "Time": 20520,
      "Track": 3
    },
    {
      "Time": 20520,
      "Track": 4
    },
    {
      "Time": 20520,
      "Track": 1
    },
    {
      "Time": 20619,
      "Track": 2
    },
    {
      "Time": 20718,
      "Track": 3
    },
    {
      "Duration": 296,
      "Time": 20816,
      "Track": 4
    },
    {
      "Time": 20915,
      "Track": 3
    },
    {
      "Time": 20915,
      "Track": 2
    },
    {
      "Time": 20915,
      "Track": 1
    },
    {
      "Time": 21112,
      "Track": 1
    },
    {
      "Time": 21310,
      "Track": 3
    },
    {
      "Time": 21310,
      "Track": 4
    },
    {
      "Time": 21408,
      "Track": 2
    },
    {
      "Time": 21507,
      "Track": 1
    },
    {
      "Duration": 296,
      "Time": 21606,
      "Track": 3
    },
    {
      "Time": 21704,
      "Track": 4
    },
    {
      "Time": 21704,
      "Track": 1
    },
    {
      "Time": 21704,
      "Track": 2
    },
    {
      "Time": 21902,
      "Track": 2
    },
    {
      "Time": 22000,
      "Track": 4
    },
    {
      "Time": 22099,
      "Track": 3
    },
    {
      "Time": 22099,
      "Track": 1
    },
    {
      "Time": 22198,
      "Track": 2
    },
    {
      "Time": 22296,
      "Track": 4
    },
    {
      "Duration": 296,
      "Time": 22395,
      "Track": 1
    },
    {
      "Time": 22494,
      "Track": 2
    },
    {
      "Time": 22494,
      "Track": 3
    },
    {
      "Time": 22494,
      "Track": 4
    },
    {
      "Time": 22691,
      "Track": 3
    },
    {
      "Time": 22790,
      "Track": 1
    },
    {
      "Time": 22889,
      "Track": 4
    },
    {
      "Time": 22889,
      "Track": 2
    },
    {
      "Time": 22987,
      "Track": 1
    },
    {
      "Time": 23086,
      "Track": 3
    },
    {
      "Duration": 296,
      "Time": 23185,
      "Track": 2
    },
    {
      "Time": 23283,
      "Track": 4
    },
    {
      "Time": 23283,
      "Track": 3
    },
    {
      "Duration": 395,
      "Time": 23283,
      "Track": 1
    },
    {
      "Time": 23481,
      "Track": 4
    },
    {
      "Time": 23678,
      "Track": 3
    },
    {
      "Duration": 197,
      "Time": 23678,
      "Track": 2
    },
    {
      "Duration": 198,
      "Time": 23875,
      "Track": 4
    },
    {
      "Time": 24073,
      "Track": 3
    },
    {
      "Time": 24073,
      "Track": 2
    },
    {
      "Duration": 197,
      "Time": 24073,
      "Track": 1
    },
    {
      "Time": 24171,
      "Track": 4
    },
    {
      "Duration": 198,
      "Time": 24270,
      "Track": 3
    },
    {
      "Duration": 296,
      "Time": 24468,
      "Track": 2
    },
    {
      "Time": 24468,
      "Track": 4
    },
    {
      "Time": 24665,
      "Track": 3
    },
    {
      "Duration": 98,
      "Time": 24764,
      "Track": 1
    },
    {
      "Time": 24862,
      "Track": 2
    },
    {
      "Time": 24862,
      "Track": 3
    },
    {
      "Time": 24862,
      "Track": 4
    },
    {
      "Time": 25060,
      "Track": 1
    },
    {
      "Time": 25158,
      "Track": 2
    },
    {
      "Time": 25257,
      "Track": 4
    },
    {
      "Duration": 197,
      "Time": 25257,
      "Track": 3
    },
    {
      "Duration": 198,
      "Time": 25454,
      "Track": 2
    },
    {
      "Duration": 197,
      "Time": 25652,
      "Track": 4
    },
    {
      "Time": 25652,
      "Track": 1
    },
    {
      "Time": 25652,
      "Track": 3
    },
    {
      "Time": 25750,
      "Track": 2
    },
    {
      "Duration": 197,
      "Time": 25849,
      "Track": 1
    },
    {
      "Time": 26046,
      "Track": 3
    },
    {
      "Time": 26046,
      "Track": 4
    },
    {
      "Time": 26244,
      "Track": 1
    },
    {
      "Time": 26244,
      "Track": 2
    },
    {
      "Time": 26343,
      "Track": 3
    },
    {
      "Time": 26441,
      "Track": 1
    },
    {
      "Time": 26441,
      "Track": 4
    },
    {
      "Time": 26540,
      "Track": 2
    },
    {
      "Time": 26540,
      "Track": 3
    },
    {
      "Time": 26639,
      "Track": 4
    },
    {
      "Time": 26639,
      "Track": 1
    },
    {
      "Time": 26737,
      "Track": 2
    },
    {
      "Time": 26836,
      "Track": 4
    },
    {
      "Time": 26836,
      "Track": 1
    },
    {
      "Duration": 296,
      "Time": 26836,
      "Track": 3
    },
    {
      "Duration": 296,
      "Time": 27033,
      "Track": 2
    },
    {
      "Duration": 296,
      "Time": 27231,
      "Track": 3
    },
    {
      "Time": 27231,
      "Track": 4
    },
    {
      "Time": 27231,
      "Track": 1
    },
    {
      "Duration": 395,
      "Time": 27428,
      "Track": 2
    },
    {
      "Time": 27625,
      "Track": 3
    },
    {
      "Duration": 296,
      "Time": 27625,
      "Track": 4
    },
    {
      "Time": 27823,
      "Track": 1
    },
    {
      "Duration": 99,
      "Time": 27921,
      "Track": 3
    },
    {
      "Time": 28020,
      "Track": 2
    },
    {
      "Time": 28020,
      "Track": 1
    },
    {
      "Time": 28020,
      "Track": 4
    },
    {
      "Duration": 493,
      "Time": 28218,
      "Track": 3
    },
    {
      "Time": 28415,
      "Track": 4
    },
    {
      "Time": 28415,
      "Track": 1
    },
    {
      "Duration": 395,
      "Time": 28612,
      "Track": 2
    },
    {
      "Duration": 197,
      "Time": 28810,
      "Track": 1
    },
    {
      "Time": 28810,
      "Track": 3
    },
    {
      "Time": 28810,
      "Track": 4
    },
    {
      "Duration": 395,
      "Time": 29007,
      "Track": 4
    },
    {
      "Duration": 198,
      "Time": 29204,
      "Track": 3
    },
    {
      "Time": 29204,
      "Track": 1
    },
    {
      "Time": 29402,
      "Track": 2
    },
    {
      "Time": 29500,
      "Track": 1
    },
    {
      "Time": 29599,
      "Track": 4
    },
    {
      "Duration": 395,
      "Time": 29599,
      "Track": 3
    },
    {
      "Duration": 296,
      "Time": 29599,
      "Track": 2
    },
    {
      "Time": 29796,
      "Track": 4
    },
    {
      "Time": 29994,
      "Track": 2
    },
    {
      "Duration": 296,
      "Time": 29994,
      "Track": 1
    },
    {
      "Duration": 296,
      "Time": 30191,
      "Track": 3
    },
    {
      "Duration": 296,
      "Time": 30389,
      "Track": 1
    },
    {
      "Time": 30389,
      "Track": 4
    },
    {
      "Time": 30389,
      "Track": 2
    },
    {
      "Duration": 395,
      "Time": 30586,
      "Track": 3
    },
    {
      "Time": 30783,
      "Track": 1
    },
    {
      "Duration": 296,
      "Time": 30783,
      "Track": 2
    },
    {
      "Time": 30981,
      "Track": 4
    },
    {
      "Duration": 99,
      "Time": 31079,
      "Track": 1
    },
    {
      "Time": 31178,
      "Track": 3
    },
    {
      "Time": 31178,
      "Track": 2
    },
    {
      "Time": 31178,
      "Track": 4
    },
    {
      "Duration": 494,
      "Time": 31375,
      "Track": 3
    },
    {
      "Time": 31573,
      "Track": 2
    },
    {
      "Time": 31573,
      "Track": 1
    },
    {
      "Duration": 395,
      "Time": 31770,
      "Track": 1
    },
    {
      "Duration": 197,
      "Time": 31968,
      "Track": 4
    },
    {
      "Time": 31968,
      "Track": 3
    },
    {
      "Time": 31968,
      "Track": 2
    },
    {
      "Duration": 395,
      "Time": 32165,
      "Track": 2
    },
    {
      "Duration": 198,
      "Time": 32362,
      "Track": 3
    },
    {
      "Time": 32362,
      "Track": 4
    },
    {
      "Time": 32560,
      "Track": 1
    },
    {
      "Time": 32658,
      "Track": 4
    },
    {
      "Time": 32757,
      "Track": 2
    },
    {
      "Time": 32757,
      "Track": 1
    },
    {
      "Duration": 395,
      "Time": 32757,
      "Track": 3
    },
    {
      "Time": 32954,
      "Track": 4
    },
    {
      "Time": 33152,
      "Track": 2
    },
    {
      "Time": 33152,
      "Track": 4
    },
    {
      "Duration": 197,
      "Time": 33152,
      "Track": 1
    },
    {
      "Time": 33250,
      "Track": 3
    },
    {
      "Duration": 197,
      "Time": 33349,
      "Track": 2
    },
    {
      "Time": 33546,
      "Track": 3
    },
    {
      "Time": 33546,
      "Track": 1
    },
    {
      "Duration": 198,
      "Time": 33546,
      "Track": 4
    },
    {
      "Duration": 197,
      "Time": 33744,
      "Track": 3
    },
    {
      "Time": 33941,
      "Track": 4
    },
    {
      "Duration": 296,
      "Time": 33941,
      "Track": 1
    },
    {
      "Time": 34139,
      "Track": 3
    },
    {
      "Duration": 99,
      "Time": 34237,
      "Track": 2
    },
    {
      "Time": 34336,
      "Track": 3
    },
    {
      "Time": 34336,
      "Track": 4
    },
    {
      "Time": 34336,
      "Track": 1
    },
    {
      "Duration": 494,
      "Time": 34533,
      "Track": 4
    },
    {
      "Time": 34632,
      "Track": 2
    },
    {
      "Time": 34731,
      "Track": 3
    },
    {
      "Duration": 197,
      "Time": 34731,
      "Track": 1
    },
    {
      "Duration": 197,
      "Time": 34928,
      "Track": 2
    },
    {
      "Time": 35125,
      "Track": 4
    },
    {
      "Time": 35125,
      "Track": 1
    },
    {
      "Duration": 198,
      "Time": 35125,
      "Track": 3
    },
    {
      "Duration": 197,
      "Time": 35323,
      "Track": 2
    },
    {
      "Duration": 198,
      "Time": 35520,
      "Track": 4
    },
    {
      "Time": 35520,
      "Track": 1
    },
    {
      "Time": 35718,
      "Track": 3
    },
    {
      "Time": 35816,
      "Track": 2
    },
    {
      "Time": 35915,
      "Track": 3
    },
    {
      "Time": 35915,
      "Track": 1
    },
    {
      "Duration": 395,
      "Time": 35915,
      "Track": 4
    },
    {
      "Time": 36112,
      "Track": 2
    },
    {
      "Time": 36310,
      "Track": 3
    },
    {
      "Duration": 197,
      "Time": 36310,
      "Track": 1
    },
    {
      "Time": 36408,
      "Track": 2
    },
    {
      "Duration": 197,
      "Time": 36507,
      "Track": 3
    },
    {
      "Duration": 198,
      "Time": 36704,
      "Track": 2
    },
    {
      "Time": 36704,
      "Track": 4
    },
    {
      "Time": 36704,
      "Track": 1
    },
    {
      "Duration": 197,
      "Time": 36902,
      "Track": 4
    },
    {
      "Time": 37099,
      "Track": 1
    },
    {
      "Duration": 296,
      "Time": 37099,
      "Track": 3
    },
    {
      "Time": 37296,
      "Track": 4
    },
    {
      "Duration": 99,
      "Time": 37395,
      "Track": 2
    },
    {
      "Time": 37494,
      "Track": 1
    },
    {
      "Time": 37494,
      "Track": 3
    },
    {
      "Time": 37494,
      "Track": 4
    },
    {
      "Duration": 494,
      "Time": 37691,
      "Track": 1
    },
    {
      "Time": 37790,
      "Track": 2
    },
    {
      "Time": 37889,
      "Track": 3
    },
    {
      "Duration": 197,
      "Time": 37889,
      "Track": 4
    },
    {
      "Duration": 197,
      "Time": 38086,
      "Track": 2
    },
    {
      "Time": 38283,
      "Track": 4
    },
    {
      "Time": 38283,
      "Track": 1
    },
    {
      "Duration": 198,
      "Time": 38283,
      "Track": 3
    },
    {
      "Duration": 197,
      "Time": 38481,
      "Track": 1
    },
    {
      "Time": 38678,
      "Track": 2
    },
    {
      "Duration": 197,
      "Time": 38678,
      "Track": 4
    },
    {
      "Time": 38875,
      "Track": 3
    },
    {
      "Time": 38974,
      "Track": 1
    },
    {
      "Time": 39073,
      "Track": 2
    },
    {
      "Time": 39073,
      "Track": 4
    },
    {
      "Duration": 395,
      "Time": 39073,
      "Track": 3
    },
    {
      "Time": 39270,
      "Track": 1
    },
    {
      "Time": 39468,
      "Track": 2
    },
    {
      "Time": 39468,
      "Track": 1
    },
    {
      "Time": 39468,
      "Track": 4
    },
    {
      "Time": 39566,
      "Track": 3
    },
    {
      "Time": 39665,
      "Track": 2
    },
    {
      "Duration": 296,
      "Time": 39764,
      "Track": 4
    },
    {
      "Time": 39862,
      "Track": 3
    },
    {
      "Time": 39862,
      "Track": 2
    },
    {
      "Time": 39862,
      "Track": 1
    },
    {
      "Time": 40060,
      "Track": 1
    },
    {
      "Time": 40257,
      "Track": 3
    },
    {
      "Time": 40257,
      "Track": 4
    },
    {
      "Time": 40356,
      "Track": 2
    },
    {
      "Time": 40454,
      "Track": 1
    },
    {
      "Duration": 296,
      "Time": 40553,
      "Track": 3
    },
    {
      "Time": 40652,
      "Track": 2
    },
    {
      "Time": 40652,
      "Track": 4
    },
    {
      "Time": 40652,
      "Track": 1
    },
    {
      "Time": 40849,
      "Track": 2
    },
    {
      "Time": 41046,
      "Track": 4
    },
    {
      "Time": 41046,
      "Track": 1
    },
    {
      "Time": 41145,
      "Track": 3
    },
    {
      "Time": 41244,
      "Track": 2
    },
    {
      "Duration": 296,
      "Time": 41343,
      "Track": 1
    },
    {
      "Time": 41441,
      "Track": 2
    },
    {
      "Time": 41441,
      "Track": 3
    },
    {
      "Time": 41441,
      "Track": 4
    },
    {
      "Time": 41639,
      "Track": 3
    },
    {
      "Time": 41836,
      "Track": 1
    },
    {
      "Time": 41836,
      "Track": 2
    },
    {
      "Time": 41935,
      "Track": 4
    },
    {
      "Time": 42033,
      "Track": 3
    },
    {
      "Duration": 296,
      "Time": 42132,
      "Track": 2
    },
    {
      "Time": 42231,
      "Track": 3
    },
    {
      "Time": 42231,
      "Track": 1
    },
    {
      "Duration": 394,
      "Time": 42231,
      "Track": 4
    },
    {
      "Time": 42428,
      "Track": 1
    },
    {
      "Time": 42625,
      "Track": 2
    },
    {
      "Duration": 198,
      "Time": 42625,
      "Track": 3
    },
    {
      "Duration": 197,
      "Time": 42823,
      "Track": 1
    },
    {
      "Time": 43020,
      "Track": 2
    },
    {
      "Time": 43020,
      "Track": 3
    },
    {
      "Duration": 198,
      "Time": 43020,
      "Track": 4
    },
    {
      "Time": 43119,
      "Track": 1
    },
    {
      "Duration": 197,
      "Time": 43218,
      "Track": 2
    },
    {
      "Time": 43316,
      "Track": 3
    },
    {
      "Time": 43415,
      "Track": 4
    },
    {
      "Duration": 296,
      "Time": 43415,
      "Track": 1
    },
    {
      "Time": 43612,
      "Track": 2
    },
    {
      "Duration": 99,
      "Time": 43711,
      "Track": 3
    },
    {
      "Time": 43810,
      "Track": 2
    },
    {
      "Time": 43810,
      "Track": 1
    },
    {
      "Time": 43810,
      "Track": 4
    },
    {
      "Time": 44007,
      "Track": 3
    },
    {
      "Time": 44106,
      "Track": 2
    },
    {
      "Time": 44204,
      "Track": 3
    },
    {
      "Duration": 198,
      "Time": 44204,
      "Track": 4
    },
    {
      "Duration": 98,
      "Time": 44402,
      "Track": 1
    },
    {
      "Time": 44500,
      "Track": 2
    },
    {
      "Time": 44599,
      "Track": 1
    },
    {
      "Time": 44599,
      "Track": 4
    },
    {
      "Duration": 197,
      "Time": 44599,
      "Track": 3
    },
    {
      "Time": 44698,
      "Track": 2
    },
    {
      "Duration": 198,
      "Time": 44796,
      "Track": 1
    },
    {
      "Time": 44895,
      "Track": 4
    },
    {
      "Time": 44994,
      "Track": 2
    },
    {
      "Duration": 197,
      "Time": 44994,
      "Track": 3
    },
    {
      "Time": 45191,
      "Track": 4
    },
    {
      "Time": 45191,
      "Track": 1
    },
    {
      "Time": 45290,
      "Track": 2
    },
    {
      "Time": 45290,
      "Track": 3
    },
    {
      "Time": 45389,
      "Track": 4
    },
    {
      "Time": 45389,
      "Track": 1
    },
    {
      "Time": 45586,
      "Track": 2
    },
    {
      "Time": 45586,
      "Track": 3
    },
    {
      "Time": 45586,
      "Track": 4
    },
    {
      "Time": 45783,
      "Track": 1
    },
    {
      "Time": 45783,
      "Track": 2
    },
    {
      "Time": 45783,
      "Track": 3
    },
    {
      "Time": 45981,
      "Track": 4
    },
    {
      "Time": 46178,
      "Track": 3
    },
    {
      "Time": 46178,
      "Track": 4
    },
    {
      "Time": 46277,
      "Track": 2
    },
    {
      "Time": 46277,
      "Track": 1
    },
    {
      "Time": 46375,
      "Track": 3
    },
    {
      "Time": 46375,
      "Track": 4
    },
    {
      "Time": 46573,
      "Track": 2
    },
    {
      "Time": 46573,
      "Track": 1
    },
    {
      "Time": 46770,
      "Track": 3
    },
    {
      "Time": 46869,
      "Track": 2
    },
    {
      "Duration": 296,
      "Time": 46968,
      "Track": 4
    },
    {
      "Time": 47165,
      "Track": 1
    },
    {
      "Time": 47264,
      "Track": 2
    },
    {
      "Time": 47362,
      "Track": 3
    },
    {
      "Time": 47362,
      "Track": 1
    },
    {
      "Time": 47362,
      "Track": 4
    },
    {
      "Time": 47560,
      "Track": 2
    },
    {
      "Time": 47757,
      "Track": 3
    },
    {
      "Time": 47757,
      "Track": 1
    },
    {
      "Time": 47856,
      "Track": 2
    },
    {
      "Time": 47856,
      "Track": 4
    },
    {
      "Time": 47954,
      "Track": 3
    },
    {
      "Time": 47954,
      "Track": 1
    },
    {
      "Time": 48152,
      "Track": 2
    },
    {
      "Time": 48152,
      "Track": 4
    },
    {
      "Duration": 99,
      "Time": 48349,
      "Track": 3
    },
    {
      "Duration": 99,
      "Time": 48349,
      "Track": 4
    },
    {
      "Duration": 198,
      "Time": 48546,
      "Track": 4
    },
    {
      "Duration": 198,
      "Time": 48546,
      "Track": 3
    },
    {
      "Time": 48744,
      "Track": 1
    },
    {
      "Time": 48843,
      "Track": 3
    },
    {
      "Time": 48941,
      "Track": 4
    },
    {
      "Time": 48941,
      "Track": 2
    },
    {
      "Time": 48941,
      "Track": 1
    },
    {
      "Time": 49139,
      "Track": 3
    },
    {
      "Time": 49336,
      "Track": 4
    },
    {
      "Time": 49336,
      "Track": 1
    },
    {
      "Time": 49435,
      "Track": 2
    },
    {
      "Time": 49435,
      "Track": 3
    },
    {
      "Time": 49533,
      "Track": 4
    },
    {
      "Time": 49533,
      "Track": 1
    },
    {
      "Time": 49731,
      "Track": 2
    },
    {
      "Time": 49731,
      "Track": 3
    },
    {
      "Time": 49928,
      "Track": 4
    },
    {
      "Time": 50027,
      "Track": 1
    },
    {
      "Duration": 296,
      "Time": 50125,
      "Track": 2
    },
    {
      "Time": 50323,
      "Track": 3
    },
    {
      "Time": 50421,
      "Track": 4
    },
    {
      "Time": 50520,
      "Track": 3
    },
    {
      "Time": 50520,
      "Track": 1
    },
    {
      "Time": 50520,
      "Track": 2
    },
    {
      "Time": 50718,
      "Track": 4
    },
    {
      "Time": 50915,
      "Track": 2
    },
    {
      "Time": 50915,
      "Track": 1
    },
    {
      "Time": 51014,
      "Track": 3
    },
    {
      "Time": 51014,
      "Track": 4
    },
    {
      "Time": 51112,
      "Track": 2
    },
    {
      "Time": 51112,
      "Track": 1
    },
    {
      "Time": 51310,
      "Track": 3
    },
    {
      "Time": 51310,
      "Track": 4
    },
    {
      "Duration": 99,
      "Time": 51507,
      "Track": 2
    },
    {
      "Duration": 99,
      "Time": 51507,
      "Track": 3
    },
    {
      "Time": 51606,
      "Track": 1
    },
    {
      "Time": 51606,
      "Track": 4
    },
    {
      "Duration": 198,
      "Time": 51704,
      "Track": 3
    },
    {
      "Duration": 198,
      "Time": 51704,
      "Track": 2
    },
    {
      "Time": 52099,
      "Track": 1
    },
    {
      "Time": 52099,
      "Track": 2
    },
    {
      "Time": 52099,
      "Track": 4
    },
    {
      "Time": 52198,
      "Track": 3
    },
    {
      "Time": 52296,
      "Track": 1
    },
    {
      "Time": 52395,
      "Track": 2
    },
    {
      "Time": 52494,
      "Track": 4
    },
    {
      "Time": 52494,
      "Track": 1
    },
    {
      "Time": 52494,
      "Track": 3
    },
    {
      "Time": 52593,
      "Track": 2
    },
    {
      "Time": 52691,
      "Track": 4
    },
    {
      "Time": 52691,
      "Track": 3
    },
    {
      "Time": 52889,
      "Track": 2
    },
    {
      "Time": 52889,
      "Track": 1
    },
    {
      "Time": 53086,
      "Track": 3
    },
    {
      "Time": 53185,
      "Track": 2
    },
    {
      "Duration": 296,
      "Time": 53283,
      "Track": 4
    },
    {
      "Duration": 197,
      "Time": 53481,
      "Track": 1
    },
    {
      "Time": 53678,
      "Track": 2
    },
    {
      "Time": 53678,
      "Track": 3
    },
    {
      "Time": 53678,
      "Track": 4
    },
    {
      "Time": 53875,
      "Track": 1
    },
    {
      "Time": 54073,
      "Track": 4
    },
    {
      "Time": 54073,
      "Track": 3
    },
    {
      "Time": 54171,
      "Track": 2
    },
    {
      "Time": 54171,
      "Track": 1
    },
    {
      "Time": 54270,
      "Track": 4
    },
    {
      "Time": 54270,
      "Track": 3
    },
    {
      "Time": 54468,
      "Track": 2
    },
    {
      "Time": 54468,
      "Track": 1
    },
    {
      "Time": 54665,
      "Track": 3
    },
    {
      "Time": 54665,
      "Track": 4
    },
    {
      "Time": 54665,
      "Track": 1
    },
    {
      "Time": 54862,
      "Track": 2
    },
    {
      "Time": 54862,
      "Track": 3
    },
    {
      "Time": 54862,
      "Track": 4
    },
    {
      "Time": 55060,
      "Track": 2
    },
    {
      "Time": 55060,
      "Track": 1
    },
    {
      "Time": 55257,
      "Track": 1
    },
    {
      "Duration": 691,
      "Time": 55257,
      "Track": 4
    },
    {
      "Time": 55454,
      "Track": 2
    },
    {
      "Duration": 691,
      "Time": 55652,
      "Track": 3
    },
    {
      "Time": 55652,
      "Track": 2
    },
    {
      "Time": 55652,
      "Track": 1
    },
    {
      "Time": 55849,
      "Track": 1
    },
    {
      "Time": 56046,
      "Track": 4
    },
    {
      "Duration": 691,
      "Time": 56046,
      "Track": 2
    },
    {
      "Time": 56244,
      "Track": 1
    },
    {
      "Time": 56441,
      "Track": 4
    },
    {
      "Time": 56441,
      "Track": 1
    },
    {
      "Time": 56441,
      "Track": 3
    },
    {
      "Time": 56639,
      "Track": 3
    },
    {
      "Time": 56836,
      "Track": 2
    },
    {
      "Time": 56836,
      "Track": 1
    },
    {
      "Time": 56836,
      "Track": 4
    },
    {
      "Time": 57033,
      "Track": 1
    },
    {
      "Time": 57033,
      "Track": 3
    },
    {
      "Time": 57033,
      "Track": 4
    },
    {
      "Time": 57231,
      "Track": 2
    },
    {
      "Time": 57231,
      "Track": 1
    },
    {
      "Time": 57231,
      "Track": 3
    },
    {
      "Time": 57428,
      "Track": 2
    },
    {
      "Time": 57428,
      "Track": 4
    },
    {
      "Time": 57428,
      "Track": 3
    },
    {
      "Time": 57625,
      "Track": 4
    },
    {
      "Time": 57625,
      "Track": 1
    },
    {
      "Time": 57625,
      "Track": 2
    },
    {
      "Time": 57823,
      "Track": 3
    },
    {
      "Time": 57823,
      "Track": 1
    },
    {
      "Time": 57921,
      "Track": 2
    },
    {
      "Time": 57921,
      "Track": 4
    },
    {
      "Time": 58020,
      "Track": 3
    },
    {
      "Time": 58020,
      "Track": 1
    },
    {
      "Time": 58218,
      "Track": 4
    },
    {
      "Time": 58415,
      "Track": 3
    },
    {
      "Time": 58415,
      "Track": 2
    },
    {
      "Time": 58415,
      "Track": 1
    },
    {
      "Time": 58810,
      "Track": 1
    },
    {
      "Time": 58810,
      "Track": 4
    },
    {
      "Duration": 394,
      "Time": 58810,
      "Track": 3
    },
    {
      "Time": 59204,
      "Track": 4
    },
    {
      "Time": 59204,
      "Track": 2
    },
    {
      "Time": 59204,
      "Track": 1
    },
    {
      "Time": 59402,
      "Track": 3
    },
    {
      "Time": 59468,
      "Track": 2
    },
    {
      "Time": 59533,
      "Track": 3
    },
    {
      "Time": 59599,
      "Track": 1
    },
    {
      "Time": 59796,
      "Track": 3
    },
    {
      "Time": 59796,
      "Track": 2
    },
    {
      "Time": 59895,
      "Track": 1
    },
    {
      "Time": 59994,
      "Track": 3
    },
    {
      "Time": 59994,
      "Track": 2
    },
    {
      "Time": 59994,
      "Track": 4
    },
    {
      "Time": 60191,
      "Track": 4
    },
    {
      "Time": 60191,
      "Track": 2
    },
    {
      "Time": 60191,
      "Track": 1
    },
    {
      "Time": 60389,
      "Track": 1
    },
    {
      "Time": 60389,
      "Track": 4
    },
    {
      "Time": 60389,
      "Track": 3
    },
    {
      "Time": 60586,
      "Track": 2
    },
    {
      "Time": 60586,
      "Track": 1
    },
    {
      "Time": 60586,
      "Track": 3
    },
    {
      "Time": 60783,
      "Track": 2
    },
    {
      "Time": 60783,
      "Track": 3
    },
    {
      "Time": 60783,
      "Track": 4
    },
    {
      "Time": 60981,
      "Track": 4
    },
    {
      "Time": 60981,
      "Track": 1
    },
    {
      "Time": 61079,
      "Track": 2
    },
    {
      "Time": 61079,
      "Track": 3
    },
    {
      "Time": 61178,
      "Track": 4
    },
    {
      "Time": 61178,
      "Track": 1
    },
    {
      "Time": 61375,
      "Track": 2
    },
    {
      "Time": 61573,
      "Track": 1
    },
    {
      "Time": 61573,
      "Track": 3
    },
    {
      "Duration": 296,
      "Time": 61573,
      "Track": 4
    },
    {
      "Duration": 395,
      "Time": 61770,
      "Track": 2
    },
    {
      "Time": 61968,
      "Track": 4
    },
    {
      "Time": 61968,
      "Track": 3
    },
    {
      "Duration": 296,
      "Time": 61968,
      "Track": 1
    },
    {
      "Duration": 395,
      "Time": 62165,
      "Track": 3
    },
    {
      "Time": 62362,
      "Track": 1
    },
    {
      "Duration": 296,
      "Time": 62362,
      "Track": 4
    },
    {
      "Duration": 394,
      "Time": 62560,
      "Track": 2
    },
    {
      "Time": 62757,
      "Track": 4
    },
    {
      "Time": 62757,
      "Track": 1
    },
    {
      "Duration": 296,
      "Time": 62757,
      "Track": 3
    },
    {
      "Duration": 395,
      "Time": 62954,
      "Track": 1
    },
    {
      "Time": 63152,
      "Track": 3
    },
    {
      "Duration": 296,
      "Time": 63152,
      "Track": 4
    },
    {
      "Duration": 395,
      "Time": 63349,
      "Track": 3
    },
    {
      "Duration": 297,
      "Time": 63546,
      "Track": 1
    },
    {
      "Time": 63546,
      "Track": 2
    },
    {
      "Time": 63546,
      "Track": 4
    },
    {
      "Duration": 395,
      "Time": 63744,
      "Track": 2
    },
    {
      "Duration": 296,
      "Time": 63843,
      "Track": 4
    },
    {
      "Time": 63941,
      "Track": 1
    },
    {
      "Time": 63941,
      "Track": 3
    },
    {
      "Duration": 197,
      "Time": 64139,
      "Track": 3
    },
    {
      "Time": 64336,
      "Track": 2
    },
    {
      "Time": 64336,
      "Track": 4
    },
    {
      "Duration": 197,
      "Time": 64336,
      "Track": 1
    },
    {
      "Duration": 198,
      "Time": 64533,
      "Track": 2
    },
    {
      "Time": 64731,
      "Track": 3
    },
    {
      "Duration": 690,
      "Time": 64731,
      "Track": 4
    },
    {
      "Time": 64928,
      "Track": 1
    },
    {
      "Time": 65125,
      "Track": 3
    },
    {
      "Time": 65125,
      "Track": 1
    },
    {
      "Duration": 593,
      "Time": 65125,
      "Track": 2
    },
    {
      "Time": 65323,
      "Track": 3
    },
    {
      "Time": 65520,
      "Track": 4
    },
    {
      "Duration": 198,
      "Time": 65520,
      "Track": 1
    },
    {
      "Time": 65718,
      "Track": 3
    },
    {
      "Time": 65718,
      "Track": 4
    },
    {
      "Time": 65816,
      "Track": 2
    },
    {
      "Time": 65915,
      "Track": 3
    },
    {
      "Duration": 395,
      "Time": 65915,
      "Track": 1
    },
    {
      "Duration": 395,
      "Time": 65915,
      "Track": 4
    },
    {
      "Time": 66112,
      "Track": 2
    },
    {
      "Time": 66310,
      "Track": 2
    },
    {
      "Duration": 296,
      "Time": 66310,
      "Track": 3
    },
    {
      "Duration": 395,
      "Time": 66507,
      "Track": 1
    },
    {
      "Time": 66704,
      "Track": 2
    },
    {
      "Time": 66704,
      "Track": 3
    },
    {
      "Duration": 296,
      "Time": 66704,
      "Track": 4
    },
    {
      "Duration": 197,
      "Time": 66902,
      "Track": 2
    },
    {
      "Time": 67099,
      "Track": 3
    },
    {
      "Duration": 296,
      "Time": 67099,
      "Track": 4
    },
    {
      "Duration": 198,
      "Time": 67296,
      "Track": 1
    },
    {
      "Time": 67494,
      "Track": 2
    },
    {
      "Time": 67494,
      "Track": 4
    },
    {
      "Duration": 296,
      "Time": 67494,
      "Track": 3
    },
    {
      "Duration": 198,
      "Time": 67691,
      "Track": 2
    },
    {
      "Time": 67889,
      "Track": 4
    },
    {
      "Time": 67889,
      "Track": 3
    },
    {
      "Duration": 296,
      "Time": 67889,
      "Track": 1
    },
    {
      "Duration": 395,
      "Time": 68086,
      "Track": 4
    },
    {
      "Time": 68283,
      "Track": 1
    },
    {
      "Time": 68283,
      "Track": 3
    },
    {
      "Duration": 296,
      "Time": 68283,
      "Track": 2
    },
    {
      "Duration": 394,
      "Time": 68481,
      "Track": 3
    },
    {
      "Time": 68678,
      "Track": 2
    },
    {
      "Duration": 296,
      "Time": 68678,
      "Track": 1
    },
    {
      "Duration": 395,
      "Time": 68875,
      "Track": 4
    },
    {
      "Time": 69073,
      "Track": 1
    },
    {
      "Time": 69073,
      "Track": 3
    },
    {
      "Duration": 296,
      "Time": 69073,
      "Track": 2
    },
    {
      "Duration": 198,
      "Time": 69270,
      "Track": 3
    },
    {
      "Time": 69468,
      "Track": 4
    },
    {
      "Time": 69468,
      "Track": 2
    },
    {
      "Duration": 296,
      "Time": 69468,
      "Track": 1
    },
    {
      "Duration": 395,
      "Time": 69665,
      "Track": 4
    },
    {
      "Time": 69862,
      "Track": 1
    },
    {
      "Time": 69862,
      "Track": 3
    },
    {
      "Duration": 296,
      "Time": 69862,
      "Track": 2
    },
    {
      "Duration": 98,
      "Time": 70060,
      "Track": 3
    },
    {
      "Duration": 691,
      "Time": 70158,
      "Track": 1
    },
    {
      "Time": 70257,
      "Track": 2
    },
    {
      "Time": 70257,
      "Track": 3
    },
    {
      "Time": 70257,
      "Track": 4
    },
    {
      "Time": 70454,
      "Track": 3
    },
    {
      "Time": 70652,
      "Track": 2
    },
    {
      "Time": 70652,
      "Track": 3
    },
    {
      "Time": 70652,
      "Track": 4
    },
    {
      "Time": 70849,
      "Track": 4
    },
    {
      "Time": 71046,
      "Track": 3
    },
    {
      "Duration": 346,
      "Time": 71046,
      "Track": 2
    },
    {
      "Time": 71046,
      "Track": 1
    },
    {
      "Time": 71244,
      "Track": 4
    },
    {
      "Time": 71441,
      "Track": 3
    },
    {
      "Time": 71441,
      "Track": 1
    },
    {
      "Time": 71441,
      "Track": 2
    },
    {
      "Time": 71639,
      "Track": 1
    },
    {
      "Time": 71836,
      "Track": 2
    },
    {
      "Time": 71836,
      "Track": 4
    },
    {
      "Duration": 345,
      "Time": 71836,
      "Track": 3
    },
    {
      "Time": 72033,
      "Track": 1
    },
    {
      "Time": 72231,
      "Track": 3
    },
    {
      "Time": 72231,
      "Track": 2
    },
    {
      "Time": 72231,
      "Track": 4
    },
    {
      "Time": 72428,
      "Track": 4
    },
    {
      "Time": 72625,
      "Track": 1
    },
    {
      "Time": 72625,
      "Track": 3
    },
    {
      "Duration": 346,
      "Time": 72625,
      "Track": 2
    },
    {
      "Time": 72823,
      "Track": 4
    },
    {
      "Time": 73020,
      "Track": 1
    },
    {
      "Time": 73020,
      "Track": 2
    },
    {
      "Time": 73020,
      "Track": 3
    },
    {
      "Time": 73218,
      "Track": 4
    },
    {
      "Time": 73415,
      "Track": 2
    },
    {
      "Time": 73415,
      "Track": 4
    },
    {
      "Duration": 197,
      "Time": 73415,
      "Track": 3
    },
    {
      "Time": 73612,
      "Track": 1
    },
    {
      "Time": 73612,
      "Track": 2
    },
    {
      "Time": 73711,
      "Track": 3
    },
    {
      "Time": 73711,
      "Track": 4
    },
    {
      "Time": 73810,
      "Track": 2
    },
    {
      "Duration": 197,
      "Time": 73810,
      "Track": 1
    },
    {
      "Time": 74007,
      "Track": 4
    },
    {
      "Time": 74007,
      "Track": 3
    },
    {
      "Time": 74106,
      "Track": 2
    },
    {
      "Time": 74204,
      "Track": 3
    },
    {
      "Time": 74204,
      "Track": 4
    },
    {
      "Duration": 296,
      "Time": 74204,
      "Track": 1
    },
    {
      "Duration": 394,
      "Time": 74402,
      "Track": 2
    },
    {
      "Duration": 296,
      "Time": 74599,
      "Track": 4
    },
    {
      "Time": 74599,
      "Track": 3
    },
    {
      "Time": 74599,
      "Track": 1
    },
    {
      "Duration": 395,
      "Time": 74796,
      "Track": 3
    },
    {
      "Duration": 296,
      "Time": 74994,
      "Track": 2
    },
    {
      "Time": 74994,
      "Track": 4
    },
    {
      "Duration": 395,
      "Time": 75191,
      "Track": 1
    },
    {
      "Duration": 296,
      "Time": 75389,
      "Track": 3
    },
    {
      "Time": 75389,
      "Track": 4
    },
    {
      "Time": 75389,
      "Track": 2
    },
    {
      "Duration": 395,
      "Time": 75586,
      "Track": 4
    },
    {
      "Duration": 296,
      "Time": 75783,
      "Track": 2
    },
    {
      "Time": 75783,
      "Track": 3
    },
    {
      "Duration": 394,
      "Time": 75981,
      "Track": 3
    },
    {
      "Duration": 296,
      "Time": 76178,
      "Track": 1
    },
    {
      "Time": 76178,
      "Track": 2
    },
    {
      "Time": 76178,
      "Track": 4
    },
    {
      "Duration": 395,
      "Time": 76375,
      "Track": 4
    },
    {
      "Duration": 296,
      "Time": 76474,
      "Track": 2
    },
    {
      "Time": 76573,
      "Track": 3
    },
    {
      "Time": 76573,
      "Track": 1
    },
    {
      "Duration": 198,
      "Time": 76770,
      "Track": 3
    },
    {
      "Duration": 197,
      "Time": 76968,
      "Track": 2
    },
    {
      "Time": 76968,
      "Track": 1
    },
    {
      "Time": 76968,
      "Track": 4
    },
    {
      "Duration": 197,
      "Time": 77165,
      "Track": 1
    },
    {
      "Time": 77362,
      "Track": 4
    },
    {
      "Duration": 691,
      "Time": 77362,
      "Track": 2
    },
    {
      "Time": 77560,
      "Track": 1
    },
    {
      "Time": 77757,
      "Track": 3
    },
    {
      "Time": 77757,
      "Track": 1
    },
    {
      "Duration": 592,
      "Time": 77757,
      "Track": 4
    },
    {
      "Time": 77954,
      "Track": 3
    },
    {
      "Duration": 197,
      "Time": 78152,
      "Track": 1
    },
    {
      "Time": 78152,
      "Track": 2
    },
    {
      "Time": 78349,
      "Track": 3
    },
    {
      "Time": 78349,
      "Track": 2
    },
    {
      "Time": 78448,
      "Track": 1
    },
    {
      "Time": 78546,
      "Track": 2
    },
    {
      "Duration": 395,
      "Time": 78546,
      "Track": 4
    },
    {
      "Duration": 395,
      "Time": 78546,
      "Track": 3
    },
    {
      "Time": 78744,
      "Track": 1
    },
    {
      "Duration": 296,
      "Time": 78941,
      "Track": 2
    },
    {
      "Time": 78941,
      "Track": 1
    },
    {
      "Duration": 394,
      "Time": 79139,
      "Track": 3
    },
    {
      "Duration": 296,
      "Time": 79336,
      "Track": 1
    },
    {
      "Time": 79336,
      "Track": 4
    },
    {
      "Time": 79336,
      "Track": 2
    },
    {
      "Duration": 198,
      "Time": 79533,
      "Track": 4
    },
    {
      "Duration": 296,
      "Time": 79731,
      "Track": 2
    },
    {
      "Time": 79731,
      "Track": 3
    },
    {
      "Duration": 197,
      "Time": 79928,
      "Track": 3
    },
    {
      "Duration": 296,
      "Time": 80125,
      "Track": 1
    },
    {
      "Time": 80125,
      "Track": 4
    },
    {
      "Time": 80125,
      "Track": 2
    },
    {
      "Duration": 197,
      "Time": 80323,
      "Track": 4
    },
    {
      "Duration": 296,
      "Time": 80520,
      "Track": 2
    },
    {
      "Time": 80520,
      "Track": 3
    },
    {
      "Time": 80520,
      "Track": 1
    },
    {
      "Duration": 394,
      "Time": 80718,
      "Track": 3
    },
    {
      "Duration": 296,
      "Time": 80915,
      "Track": 1
    },
    {
      "Time": 80915,
      "Track": 4
    },
    {
      "Time": 80915,
      "Track": 2
    },
    {
      "Duration": 395,
      "Time": 81112,
      "Track": 4
    },
    {
      "Duration": 296,
      "Time": 81310,
      "Track": 3
    },
    {
      "Time": 81310,
      "Track": 2
    },
    {
      "Duration": 395,
      "Time": 81507,
      "Track": 1
    },
    {
      "Duration": 296,
      "Time": 81704,
      "Track": 2
    },
    {
      "Time": 81704,
      "Track": 3
    },
    {
      "Time": 81704,
      "Track": 4
    },
    {
      "Duration": 197,
      "Time": 81902,
      "Track": 4
    },
    {
      "Time": 82099,
      "Track": 1
    },
    {
      "Time": 82099,
      "Track": 2
    },
    {
      "Duration": 296,
      "Time": 82099,
      "Track": 3
    },
    {
      "Duration": 395,
      "Time": 82296,
      "Track": 2
    },
    {
      "Time": 82494,
      "Track": 4
    },
    {
      "Time": 82494,
      "Track": 3
    },
    {
      "Duration": 296,
      "Time": 82494,
      "Track": 1
    },
    {
      "Duration": 99,
      "Time": 82691,
      "Track": 3
    },
    {
      "Duration": 691,
      "Time": 82790,
      "Track": 4
    },
    {
      "Time": 82889,
      "Track": 2
    },
    {
      "Time": 82889,
      "Track": 1
    },
    {
      "Time": 82889,
      "Track": 3
    },
    {
      "Time": 83086,
      "Track": 2
    },
    {
      "Time": 83283,
      "Track": 2
    },
    {
      "Time": 83283,
      "Track": 3
    },
    {
      "Time": 83283,
      "Track": 1
    },
    {
      "Time": 83481,
      "Track": 1
    },
    {
      "Time": 83678,
      "Track": 2
    },
    {
      "Time": 83678,
      "Track": 4
    },
    {
      "Duration": 345,
      "Time": 83678,
      "Track": 3
    },
    {
      "Time": 83875,
      "Track": 1
    },
    {
      "Time": 84073,
      "Track": 2
    },
    {
      "Time": 84073,
      "Track": 3
    },
    {
      "Time": 84073,
      "Track": 4
    },
    {
      "Time": 84270,
      "Track": 4
    },
    {
      "Time": 84468,
      "Track": 3
    },
    {
      "Time": 84468,
      "Track": 1
    },
    {
      "Duration": 345,
      "Time": 84468,
      "Track": 2
    },
    {
      "Time": 84665,
      "Track": 4
    },
    {
      "Time": 84862,
      "Track": 1
    },
    {
      "Time": 84862,
      "Track": 2
    },
    {
      "Time": 84862,
      "Track": 3
    },
    {
      "Time": 85060,
      "Track": 4
    },
    {
      "Time": 85158,
      "Track": 3
    },
    {
      "Time": 85257,
      "Track": 2
    },
    {
      "Time": 85257,
      "Track": 1
    },
    {
      "Time": 85257,
      "Track": 4
    },
    {
      "Time": 85454,
      "Track": 2
    },
    {
      "Time": 85454,
      "Track": 3
    },
    {
      "Time": 85454,
      "Track": 4
    },
    {
      "Time": 85652,
      "Track": 3
    },
    {
      "Time": 85652,
      "Track": 2
    },
    {
      "Time": 85652,
      "Track": 1
    },
    {
      "Time": 85849,
      "Track": 4
    },
    {
      "Time": 85849,
      "Track": 3
    },
    {
      "Time": 85849,
      "Track": 1
    },
    {
      "Time": 86046,
      "Track": 2
    },
    {
      "Time": 86046,
      "Track": 1
    },
    {
      "Time": 86046,
      "Track": 4
    },
    {
      "Time": 86244,
      "Track": 3
    },
    {
      "Time": 86244,
      "Track": 2
    },
    {
      "Time": 86343,
      "Track": 4
    },
    {
      "Time": 86441,
      "Track": 1
    },
    {
      "Time": 86441,
      "Track": 2
    },
    {
      "Time": 86441,
      "Track": 3
    },
    {
      "Time": 86639,
      "Track": 4
    },
    {
      "Time": 86639,
      "Track": 1
    },
    {
      "Time": 86737,
      "Track": 2
    },
    {
      "Time": 86836,
      "Track": 4
    },
    {
      "Time": 86836,
      "Track": 1
    },
    {
      "Time": 86836,
      "Track": 3
    },
    {
      "Time": 87033,
      "Track": 2
    },
    {
      "Time": 87033,
      "Track": 3
    },
    {
      "Time": 87033,
      "Track": 4
    },
    {
      "Time": 87231,
      "Track": 3
    },
    {
      "Time": 87231,
      "Track": 2
    },
    {
      "Time": 87231,
      "Track": 1
    },
    {
      "Time": 87428,
      "Track": 1
    },
    {
      "Time": 87428,
      "Track": 4
    },
    {
      "Time": 87428,
      "Track": 2
    },
    {
      "Time": 87625,
      "Track": 3
    },
    {
      "Time": 87625,
      "Track": 4
    },
    {
      "Time": 87625,
      "Track": 1
    },
    {
      "Time": 87823,
      "Track": 2
    },
    {
      "Time": 87823,
      "Track": 1
    },
    {
      "Time": 87921,
      "Track": 3
    },
    {
      "Time": 88020,
      "Track": 4
    },
    {
      "Time": 88020,
      "Track": 2
    },
    {
      "Time": 88020,
      "Track": 1
    },
    {
      "Time": 88218,
      "Track": 4
    },
    {
      "Time": 88218,
      "Track": 3
    },
    {
      "Time": 88316,
      "Track": 2
    },
    {
      "Time": 88415,
      "Track": 1
    },
    {
      "Time": 88415,
      "Track": 3
    },
    {
      "Time": 88415,
      "Track": 4
    },
    {
      "Time": 88612,
      "Track": 2
    },
    {
      "Time": 88612,
      "Track": 1
    },
    {
      "Time": 88612,
      "Track": 3
    },
    {
      "Time": 88810,
      "Track": 2
    },
    {
      "Time": 88810,
      "Track": 1
    },
    {
      "Time": 88810,
      "Track": 4
    },
    {
      "Time": 89007,
      "Track": 3
    },
    {
      "Time": 89007,
      "Track": 4
    },
    {
      "Time": 89007,
      "Track": 2
    },
    {
      "Time": 89204,
      "Track": 1
    },
    {
      "Time": 89204,
      "Track": 3
    },
    {
      "Time": 89204,
      "Track": 4
    },
    {
      "Time": 89402,
      "Track": 2
    },
    {
      "Time": 89402,
      "Track": 1
    },
    {
      "Time": 89500,
      "Track": 3
    },
    {
      "Time": 89500,
      "Track": 4
    },
    {
      "Time": 89599,
      "Track": 2
    },
    {
      "Time": 89599,
      "Track": 1
    },
    {
      "Time": 89698,
      "Track": 3
    },
    {
      "Time": 89796,
      "Track": 4
    },
    {
      "Time": 89796,
      "Track": 2
    },
    {
      "Time": 89895,
      "Track": 3
    },
    {
      "Time": 89994,
      "Track": 2
    },
    {
      "Time": 89994,
      "Track": 4
    },
    {
      "Duration": 296,
      "Time": 89994,
      "Track": 1
    },
    {
      "Duration": 296,
      "Time": 90191,
      "Track": 3
    },
    {
      "Duration": 296,
      "Time": 90389,
      "Track": 1
    },
    {
      "Time": 90389,
      "Track": 4
    },
    {
      "Time": 90389,
      "Track": 2
    },
    {
      "Duration": 395,
      "Time": 90586,
      "Track": 3
    },
    {
      "Duration": 296,
      "Time": 90783,
      "Track": 4
    },
    {
      "Time": 90783,
      "Track": 1
    },
    {
      "Time": 90981,
      "Track": 2
    },
    {
      "Duration": 99,
      "Time": 91079,
      "Track": 1
    },
    {
      "Time": 91178,
      "Track": 2
    },
    {
      "Time": 91178,
      "Track": 4
    },
    {
      "Time": 91178,
      "Track": 3
    },
    {
      "Duration": 494,
      "Time": 91375,
      "Track": 3
    },
    {
      "Time": 91573,
      "Track": 1
    },
    {
      "Time": 91573,
      "Track": 4
    },
    {
      "Duration": 395,
      "Time": 91770,
      "Track": 2
    },
    {
      "Duration": 197,
      "Time": 91968,
      "Track": 3
    },
    {
      "Time": 91968,
      "Track": 4
    },
    {
      "Time": 91968,
      "Track": 1
    },
    {
      "Duration": 395,
      "Time": 92165,
      "Track": 4
    },
    {
      "Duration": 198,
      "Time": 92362,
      "Track": 1
    },
    {
      "Time": 92362,
      "Track": 2
    },
    {
      "Time": 92560,
      "Track": 3
    },
    {
      "Time": 92658,
      "Track": 2
    },
    {
      "Time": 92757,
      "Track": 4
    },
    {
      "Duration": 296,
      "Time": 92757,
      "Track": 1
    },
    {
      "Duration": 395,
      "Time": 92757,
      "Track": 3
    },
    {
      "Time": 92954,
      "Track": 2
    },
    {
      "Time": 93152,
      "Track": 1
    },
    {
      "Duration": 296,
      "Time": 93152,
      "Track": 2
    },
    {
      "Duration": 296,
      "Time": 93349,
      "Track": 4
    },
    {
      "Duration": 395,
      "Time": 93546,
      "Track": 2
    },
    {
      "Time": 93546,
      "Track": 3
    },
    {
      "Time": 93546,
      "Track": 1
    },
    {
      "Duration": 395,
      "Time": 93744,
      "Track": 4
    },
    {
      "Duration": 296,
      "Time": 93941,
      "Track": 1
    },
    {
      "Time": 93941,
      "Track": 3
    },
    {
      "Time": 94139,
      "Track": 2
    },
    {
      "Duration": 99,
      "Time": 94237,
      "Track": 3
    },
    {
      "Time": 94336,
      "Track": 2
    },
    {
      "Time": 94336,
      "Track": 1
    },
    {
      "Time": 94336,
      "Track": 4
    },
    {
      "Duration": 494,
      "Time": 94533,
      "Track": 2
    },
    {
      "Time": 94731,
      "Track": 3
    },
    {
      "Time": 94731,
      "Track": 1
    },
    {
      "Duration": 395,
      "Time": 94928,
      "Track": 4
    },
    {
      "Duration": 198,
      "Time": 95125,
      "Track": 2
    },
    {
      "Time": 95125,
      "Track": 1
    },
    {
      "Time": 95125,
      "Track": 3
    },
    {
      "Duration": 395,
      "Time": 95323,
      "Track": 1
    },
    {
      "Duration": 198,
      "Time": 95520,
      "Track": 3
    },
    {
      "Time": 95520,
      "Track": 4
    },
    {
      "Time": 95718,
      "Track": 2
    },
    {
      "Time": 95816,
      "Track": 4
    },
    {
      "Time": 95915,
      "Track": 3
    },
    {
      "Time": 95915,
      "Track": 2
    },
    {
      "Time": 95915,
      "Track": 1
    },
    {
      "Time": 96112,
      "Track": 4
    },
    {
      "Time": 96310,
      "Track": 2
    },
    {
      "Time": 96310,
      "Track": 4
    },
    {
      "Duration": 296,
      "Time": 96310,
      "Track": 3
    },
    {
      "Duration": 296,
      "Time": 96507,
      "Track": 2
    },
    {
      "Duration": 296,
      "Time": 96704,
      "Track": 3
    },
    {
      "Time": 96704,
      "Track": 1
    },
    {
      "Time": 96704,
      "Track": 4
    },
    {
      "Duration": 394,
      "Time": 96902,
      "Track": 2
    },
    {
      "Duration": 296,
      "Time": 97099,
      "Track": 4
    },
    {
      "Time": 97099,
      "Track": 3
    },
    {
      "Time": 97296,
      "Track": 1
    },
    {
      "Duration": 99,
      "Time": 97395,
      "Track": 3
    },
    {
      "Time": 97494,
      "Track": 2
    },
    {
      "Time": 97494,
      "Track": 1
    },
    {
      "Time": 97494,
      "Track": 4
    },
    {
      "Duration": 494,
      "Time": 97691,
      "Track": 2
    },
    {
      "Time": 97889,
      "Track": 3
    },
    {
      "Time": 97889,
      "Track": 4
    },
    {
      "Duration": 395,
      "Time": 98086,
      "Track": 4
    },
    {
      "Duration": 198,
      "Time": 98283,
      "Track": 2
    },
    {
      "Time": 98283,
      "Track": 3
    },
    {
      "Time": 98283,
      "Track": 1
    },
    {
      "Duration": 394,
      "Time": 98481,
      "Track": 1
    },
    {
      "Duration": 197,
      "Time": 98678,
      "Track": 3
    },
    {
      "Time": 98678,
      "Track": 2
    },
    {
      "Time": 98875,
      "Track": 4
    },
    {
      "Time": 98974,
      "Track": 2
    },
    {
      "Time": 99073,
      "Track": 1
    },
    {
      "Duration": 395,
      "Time": 99073,
      "Track": 3
    },
    {
      "Duration": 296,
      "Time": 99073,
      "Track": 4
    },
    {
      "Time": 99270,
      "Track": 2
    },
    {
      "Time": 99468,
      "Track": 4
    },
    {
      "Duration": 296,
      "Time": 99468,
      "Track": 1
    },
    {
      "Duration": 296,
      "Time": 99665,
      "Track": 4
    },
    {
      "Duration": 296,
      "Time": 99862,
      "Track": 1
    },
    {
      "Time": 99862,
      "Track": 2
    },
    {
      "Time": 99862,
      "Track": 3
    },
    {
      "Duration": 394,
      "Time": 100060,
      "Track": 4
    },
    {
      "Time": 100257,
      "Track": 1
    },
    {
      "Duration": 296,
      "Time": 100257,
      "Track": 2
    },
    {
      "Time": 100454,
      "Track": 3
    },
    {
      "Duration": 99,
      "Time": 100553,
      "Track": 1
    },
    {
      "Time": 100652,
      "Track": 2
    },
    {
      "Time": 100652,
      "Track": 4
    },
    {
      "Time": 100652,
      "Track": 3
    },
    {
      "Duration": 494,
      "Time": 100849,
      "Track": 4
    },
    {
      "Time": 101046,
      "Track": 2
    },
    {
      "Time": 101046,
      "Track": 1
    },
    {
      "Time": 101244,
      "Track": 2
    },
    {
      "Time": 101244,
      "Track": 3
    },
    {
      "Duration": 197,
      "Time": 101244,
      "Track": 1
    },
    {
      "Time": 101441,
      "Track": 3
    },
    {
      "Time": 101441,
      "Track": 4
    },
    {
      "Time": 101540,
      "Track": 2
    },
    {
      "Time": 101540,
      "Track": 1
    },
    {
      "Duration": 394,
      "Time": 101639,
      "Track": 3
    },
    {
      "Time": 101639,
      "Track": 4
    },
    {
      "Duration": 197,
      "Time": 101836,
      "Track": 2
    },
    {
      "Time": 101836,
      "Track": 1
    },
    {
      "Time": 102033,
      "Track": 4
    },
    {
      "Time": 102033,
      "Track": 1
    },
    {
      "Time": 102132,
      "Track": 2
    },
    {
      "Time": 102132,
      "Track": 3
    },
    {
      "Time": 102231,
      "Track": 4
    },
    {
      "Time": 102231,
      "Track": 1
    },
    {
      "Time": 102428,
      "Track": 2
    },
    {
      "Time": 102428,
      "Track": 3
    },
    {
      "Time": 102428,
      "Track": 4
    },
    {
      "Time": 102625,
      "Track": 3
    },
    {
      "Time": 102625,
      "Track": 2
    },
    {
      "Time": 102625,
      "Track": 1
    },
    {
      "Time": 103020,
      "Track": 1
    },
    {
      "Time": 103612,
      "Track": 4
    },
    {
      "Time": 103810,
      "Track": 2
    },
    {
      "Time": 103810,
      "Track": 3
    },
    {
      "Time": 104007,
      "Track": 1
    },
    {
      "Time": 104007,
      "Track": 4
    },
    {
      "Time": 104106,
      "Track": 2
    },
    {
      "Time": 104204,
      "Track": 1
    },
    {
      "Time": 104204,
      "Track": 4
    },
    {
      "Time": 104204,
      "Track": 3
    },
    {
      "Time": 104500,
      "Track": 2
    },
    {
      "Time": 104500,
      "Track": 3
    },
    {
      "Time": 104500,
      "Track": 4
    },
    {
      "Time": 104796,
      "Track": 2
    },
    {
      "Time": 104796,
      "Track": 1
    },
    {
      "Time": 104796,
      "Track": 3
    },
    {
      "Time": 104994,
      "Track": 2
    },
    {
      "Time": 104994,
      "Track": 1
    },
    {
      "Time": 105093,
      "Track": 3
    },
    {
      "Time": 105093,
      "Track": 4
    },
    {
      "Time": 105191,
      "Track": 2
    },
    {
      "Time": 105191,
      "Track": 1
    },
    {
      "Time": 105389,
      "Track": 3
    },
    {
      "Time": 105389,
      "Track": 4
    },
    {
      "Time": 105586,
      "Track": 2
    },
    {
      "Time": 105586,
      "Track": 3
    },
    {
      "Time": 105586,
      "Track": 4
    }
  ]
}